yoda/__init__.py
yoda/cli.py
yoda/core/__init__.py
yoda/core/indexer.py
yoda/core/model_manager.py
yoda/core/seek_engine.py
yoda/core/wisdom.py
yoda/utils/__init__.py
yoda/utils/config.py
yoda/utils/file_parser.py
yoda_cli-0.1.1.dist-info/licenses/LICENSE
yoda_cli-0.1.1.dist-info/METADATA
yoda_cli-0.1.1.dist-info/WHEEL
yoda_cli-0.1.1.dist-info/entry_points.txt
yoda_cli-0.1.1.dist-info/top_level.txt
yoda_cli-0.1.1.dist-info/RECORD
